spritesheet/__init__.py
spritesheet/spriteutil.py
spritesheet_lecuong91-0.0.2.dist-info/DESCRIPTION.rst
spritesheet_lecuong91-0.0.2.dist-info/METADATA
spritesheet_lecuong91-0.0.2.dist-info/RECORD
spritesheet_lecuong91-0.0.2.dist-info/WHEEL
spritesheet_lecuong91-0.0.2.dist-info/metadata.json
spritesheet_lecuong91-0.0.2.dist-info/top_level.txt
