Metadata-Version: 2.0
Name: spritesheet-lecuong91
Version: 0.0.2
Summary: Sprite detect
Home-page: https://github.com/intek-training-jsc/sprite-sheet-cuongle91/
Author: Le Cuong
Author-email: cuong.le@f4.intek.edu.vn
License: UNKNOWN
Platform: UNKNOWN
Classifier: Programming Language :: Python :: 3
Classifier: License :: OSI Approved :: MIT License
Classifier: Operating System :: OS Independent
Requires-Python: >=3.6
Requires-Dist: setuptools
Requires-Dist: wheel
Requires-Dist: twine
Requires-Dist: numpy
Requires-Dist: pillow
